Classfile /Users/zonghengma/Documents/UCLA/capstone_new/call-graph-analysis/reachability-analysis/src/test/resources/classcollapser/ldc/A.class
  Last modified Jan 10, 2019; size 151 bytes
  MD5 checksum db29ee8e5853e1e9c7ad6c43ab70ccc7
  Compiled from "A.java"
class A
  minor version: 0
  major version: 46
  flags: ACC_SUPER
Constant pool:
   #1 = Methodref          #11.#6         // java/lang/Object."<init>":()V
   #2 = Utf8               java/lang/Object
   #3 = Utf8               SourceFile
   #4 = Utf8               A
   #5 = Utf8               <init>
   #6 = NameAndType        #5:#9          // "<init>":()V
   #7 = Utf8               Code
   #8 = Class              #4             // A
   #9 = Utf8               ()V
  #10 = Utf8               A.java
  #11 = Class              #2             // java/lang/Object
{
  A();
    descriptor: ()V
    flags:
    Code:
      stack=1, locals=1, args_size=1
         0: aload_0
         1: astore_0
         2: aload_0
         3: invokespecial #1                  // Method java/lang/Object."<init>":()V
         6: goto          9
         9: return
}
SourceFile: "A.java"
