Classfile /Users/zonghengma/Documents/UCLA/capstone_new/call-graph-analysis/reachability-analysis/src/test/resources/classcollapser/ldc/A.class
  Last modified Jan 10, 2019; size 176 bytes
  MD5 checksum f35fe1f44d02cd491e6561a30327ceb5
  Compiled from "A.java"
public class A
  minor version: 0
  major version: 52
  flags: ACC_PUBLIC, ACC_SUPER
Constant pool:
   #1 = Methodref          #3.#10         // java/lang/Object."<init>":()V
   #2 = Class              #11            // A
   #3 = Class              #12            // java/lang/Object
   #4 = Utf8               <init>
   #5 = Utf8               ()V
   #6 = Utf8               Code
   #7 = Utf8               LineNumberTable
   #8 = Utf8               SourceFile
   #9 = Utf8               A.java
  #10 = NameAndType        #4:#5          // "<init>":()V
  #11 = Utf8               A
  #12 = Utf8               java/lang/Object
{
  public A();
    descriptor: ()V
    flags: ACC_PUBLIC
    Code:
      stack=1, locals=1, args_size=1
         0: aload_0
         1: invokespecial #1                  // Method java/lang/Object."<init>":()V
         4: return
      LineNumberTable:
        line 1: 0
}
SourceFile: "A.java"
